forks_sync/__init__.py
forks_sync/_version.py
forks_sync/cli.py
forks_sync/constants.py
forks_sync/py.typed
forks_sync/sync.py
forks_sync-4.2.2.dist-info/LICENSE
forks_sync-4.2.2.dist-info/METADATA
forks_sync-4.2.2.dist-info/WHEEL
forks_sync-4.2.2.dist-info/entry_points.txt
forks_sync-4.2.2.dist-info/top_level.txt
forks_sync-4.2.2.dist-info/RECORD
