Metadata-Version: 2.1
Name: forks-sync
Version: 4.2.2
Summary: Keep all your git forks up to date with the remote default branch.
Home-page: http://github.com/justintime50/forks-sync
Author: Justintime50
License: MIT
Classifier: Programming Language :: Python :: 3
Classifier: License :: OSI Approved :: MIT License
Classifier: Operating System :: OS Independent
Requires-Python: >=3.8, <4
License-File: LICENSE
Requires-Dist: PyGithub >=1.59.0
Requires-Dist: woodchips ==1.*
Provides-Extra: dev
Requires-Dist: bandit ==1.7.* ; extra == 'dev'
Requires-Dist: black ==23.* ; extra == 'dev'
Requires-Dist: build ==0.10.* ; extra == 'dev'
Requires-Dist: flake8 ==6.* ; extra == 'dev'
Requires-Dist: isort ==5.* ; extra == 'dev'
Requires-Dist: mypy ==1.5.* ; extra == 'dev'
Requires-Dist: pytest ==7.* ; extra == 'dev'
Requires-Dist: pytest-cov ==4.* ; extra == 'dev'
Requires-Dist: twine ==4.* ; extra == 'dev'
